django_smarturlfield-1.0.4.dist-info/METADATA
django_smarturlfield-1.0.4.dist-info/RECORD
django_smarturlfield-1.0.4.dist-info/WHEEL
django_smarturlfield-1.0.4.dist-info/top_level.txt
smarturlfield/__init__.py
smarturlfield/idn.py
