Metadata-Version: 2.1
Name: django-smarturlfield
Version: 1.0.4
Summary: Django model and form fields that performs URL normalization. For example it adds 'http://' prefix and forces punicode encoding.
Home-page: https://github.com/shantilabs/django-smarturlfield
Author: Maxim Oransky
Author-email: maxim.oransky@gmail.com
License: UNKNOWN
Keywords: django,django-fields,url
Platform: UNKNOWN
Classifier: Framework :: Django :: 1.10
Classifier: Framework :: Django :: 1.11
Classifier: Framework :: Django :: 1.9
Classifier: Framework :: Django
Classifier: Programming Language :: Python :: 2.7
Classifier: Programming Language :: Python :: 3.5
Classifier: Programming Language :: Python :: 3.6
